MANIFEST.in
README.md
basestationHOWTO.txt
basestation_startup
server_startup
setup.py
teleceptorcmd
config/defaults.json
database/base_station.db
database/blank.txt
teleceptor/__init__.py
teleceptor/__init__.pyc
teleceptor/auth.py
teleceptor/auth.pyc
teleceptor/models.py
teleceptor/models.pyc
teleceptor/pages.py
teleceptor/pages.pyc
teleceptor/server.py
teleceptor/sessionManager.py
teleceptor/sessionManager.pyc
teleceptor/testFixtures.py
teleceptor/testFixtures.pyc
teleceptor/version.py
teleceptor/version.pyc
teleceptor/whisperUtils.py
teleceptor/whisperUtils.pyc
teleceptor.egg-info/PKG-INFO
teleceptor.egg-info/SOURCES.txt
teleceptor.egg-info/dependency_links.txt
teleceptor.egg-info/not-zip-safe
teleceptor.egg-info/requires.txt
teleceptor.egg-info/top_level.txt
teleceptor/api/__init__.py
teleceptor/api/__init__.pyc
teleceptor/api/datastreams.py
teleceptor/api/datastreams.pyc
teleceptor/api/delegation.py
teleceptor/api/delegation.pyc
teleceptor/api/messages.py
teleceptor/api/messages.pyc
teleceptor/api/readings.py
teleceptor/api/readings.pyc
teleceptor/api/sensors.py
teleceptor/api/sensors.pyc
teleceptor/basestation/__init__.py
teleceptor/basestation/__init__.pyc
teleceptor/basestation/poller.py
teleceptor/basestation/queryer.py
teleceptor/basestation/tcpPoller.py
teleceptor/basestation/tcpSensor.py
teleceptor/basestation/tcpSensor.pyc
teleceptor/softSensors/__init__.py
teleceptor/softSensors/BitcoinSensor/BTCMote.py
teleceptor/softSensors/BitcoinSensor/__init__.py
teleceptor/softSensors/SimpleInput/__init__.py
teleceptor/softSensors/SimpleInput/simpleInput.py
templates/base.html
templates/generateJson.html
templates/graph.html
templates/login.html
templates/sensor.html
templates/sensorsIndex.html
templates/timeControls.html
webroot/css/graphWidget.css
webroot/css/ie10mobile.css
webroot/css/login.css
webroot/css/sensor.css
webroot/css/sensors.css
webroot/css/starterkit.css
webroot/img/spinner.gif
webroot/js/custom-bindings.js
webroot/js/extenders.js
webroot/js/generateJson.js
webroot/js/graph.js
webroot/js/graphWidget.js
webroot/js/index.js
webroot/js/sensor.js
webroot/js/timeControls.js
webroot/js/urlHelpers.js
webroot/lib/bootstrap-switch-master/CNAME
