Metadata-Version: 1.1
Name: teleceptor
Version: 0.7.7
Summary: Data collection web application for microcontrollers
Home-page: https://github.com/visgence/teleceptor
Author: Visgnece Inc.
Author-email: info@visgence.com
License: GPL3
Download-URL: https://github.com/visgence/teleceptor/tarball/0.7.7
Platform: any
